igra/__init__.py
igra/download.py
igra/interp.py
igra/read.py
igra/support.py
igra/test_igra.py
igra-23.5.dist-info/LICENSE
igra-23.5.dist-info/METADATA
igra-23.5.dist-info/WHEEL
igra-23.5.dist-info/top_level.txt
igra-23.5.dist-info/RECORD
