Metadata-Version: 2.1
Name: igra
Version: 23.5
Summary: IGRAv2 radiosonde tools
Home-page: https://github.com/MBlaschek/igra
Author: MB
Author-email: michael.blaschek@univie.ac.at
License: MIT
Platform: UNKNOWN
Classifier: Programming Language :: Python :: 3
Classifier: License :: OSI Approved :: MIT License
Classifier: Operating System :: OS Independent
Classifier: Development Status :: 4 - Beta
Classifier: Intended Audience :: Science/Research
Classifier: Intended Audience :: Education
Classifier: Topic :: Scientific/Engineering :: Atmospheric Science
Requires-Python: >=3.6
License-File: LICENSE
Requires-Dist: requests
Requires-Dist: numpy
Requires-Dist: pandas
Requires-Dist: xarray
